{
  "ID": "d443018b-55cd-4429-a025-31f1f5ab8314",
  "Version": "2.2.9.0",
  "Name": "beibao_gezi",
  "Content": {
    "Content": {
      "Animation": {
        "Duration": 0,
        "Speed": 1.0,
        "Timelines": [],
        "ctype": "TimelineActionData"
      },
      "AnimationList": [],
      "ObjectData": {
        "Tag": 121,
        "Children": [
          {
            "FontSize": 14,
            "ButtonText": "",
            "TextColor": {
              "R": 65,
              "G": 65,
              "B": 70
            },
            "Scale9Enable": true,
            "Scale9Width": 42,
            "Scale9Height": 14,
            "OutlineSize": 0,
            "OutlineColor": {
              "G": 0,
              "B": 0
            },
            "ShadowColor": {
              "R": 110,
              "G": 110,
              "B": 110
            },
            "ShadowOffsetX": 0,
            "ShadowOffsetY": 0,
            "TouchEnable": true,
            "AnchorPoint": {
              "ScaleX": 0.5,
              "ScaleY": 0.5
            },
            "Position": {
              "X": 41.0,
              "Y": 41.0
            },
            "Scale": {
              "ScaleX": 1.0,
              "ScaleY": 1.0
            },
            "CColor": {},
            "IconVisible": false,
            "PrePosition": {
              "X": 0.5,
              "Y": 0.5
            },
            "PreSize": {
              "X": 1.0,
              "Y": 1.0
            },
            "Tag": 673,
            "ActionTag": 856005999,
            "Size": {
              "X": 82.0,
              "Y": 82.0
            },
            "Name": "btn_sel",
            "ctype": "ButtonObjectData"
          },
          {
            "FileData": {
              "Type": "Normal",
              "Path": "images/ui/ui_71.png",
              "Plist": ""
            },
            "Scale9Width": 64,
            "Scale9Height": 64,
            "AnchorPoint": {
              "ScaleX": 0.5,
              "ScaleY": 0.5
            },
            "Position": {
              "X": 41.0,
              "Y": 41.0
            },
            "Scale": {
              "ScaleX": 1.0,
              "ScaleY": 1.0
            },
            "CColor": {},
            "IconVisible": false,
            "PrePosition": {
              "X": 0.5,
              "Y": 0.5
            },
            "PreSize": {
              "X": 0.7805,
              "Y": 0.7805
            },
            "LeftMargin": 9.0,
            "RightMargin": 9.0,
            "TopMargin": 9.0,
            "BottomMargin": 9.0,
            "Tag": 124,
            "ActionTag": 461448747,
            "Size": {
              "X": 64.0,
              "Y": 64.0
            },
            "Name": "img_gezi",
            "ctype": "ImageViewObjectData"
          },
          {
            "FileData": {
              "Type": "Normal",
              "Path": "images/ui/ui_14.png",
              "Plist": ""
            },
            "Scale9Width": 64,
            "Scale9Height": 64,
            "AnchorPoint": {
              "ScaleX": 0.5,
              "ScaleY": 0.5
            },
            "Position": {
              "X": 41.0,
              "Y": 41.0
            },
            "Scale": {
              "ScaleX": 1.0,
              "ScaleY": 1.0
            },
            "CColor": {},
            "IconVisible": false,
            "PrePosition": {
              "X": 0.5,
              "Y": 0.5
            },
            "PreSize": {
              "X": 0.7805,
              "Y": 0.7805
            },
            "LeftMargin": 9.0,
            "RightMargin": 9.0,
            "TopMargin": 9.0,
            "BottomMargin": 9.0,
            "Tag": 675,
            "ActionTag": -1494835609,
            "Size": {
              "X": 64.0,
              "Y": 64.0
            },
            "Name": "img_icon",
            "ctype": "ImageViewObjectData"
          },
          {
            "FileData": {
              "Type": "Normal",
              "Path": "images/ui/ui_15.png",
              "Plist": ""
            },
            "Scale9Enable": true,
            "Scale9OriginX": 20,
            "Scale9OriginY": 20,
            "Scale9Width": 10,
            "Scale9Height": 10,
            "AnchorPoint": {
              "ScaleX": 0.5,
              "ScaleY": 0.5
            },
            "Position": {
              "X": 41.0,
              "Y": 41.0
            },
            "Scale": {
              "ScaleX": 1.0,
              "ScaleY": 1.0
            },
            "CColor": {},
            "IconVisible": false,
            "PrePosition": {
              "X": 0.5,
              "Y": 0.5
            },
            "PreSize": {
              "X": 0.8293,
              "Y": 0.8293
            },
            "LeftMargin": 7.0,
            "RightMargin": 7.0,
            "TopMargin": 7.0,
            "BottomMargin": 7.0,
            "Tag": 123,
            "ActionTag": 573388966,
            "Size": {
              "X": 68.0,
              "Y": 68.0
            },
            "Name": "img_enter",
            "ctype": "ImageViewObjectData"
          },
          {
            "IsCustomSize": true,
            "FontSize": 16,
            "LabelText": "9999",
            "HorizontalAlignmentType": "HT_Right",
            "VerticalAlignmentType": "VT_Bottom",
            "OutlineSize": 0,
            "OutlineColor": {
              "G": 0,
              "B": 0
            },
            "ShadowColor": {
              "R": 110,
              "G": 110,
              "B": 110
            },
            "ShadowOffsetX": 0,
            "ShadowOffsetY": 0,
            "AnchorPoint": {
              "ScaleX": 1.0
            },
            "Position": {
              "X": 68.0,
              "Y": 12.0
            },
            "Scale": {
              "ScaleX": 1.0,
              "ScaleY": 1.0
            },
            "CColor": {
              "R": 0,
              "B": 0
            },
            "IconVisible": false,
            "PrePosition": {
              "X": 0.8293,
              "Y": 0.1463
            },
            "PreSize": {
              "X": 0.6098,
              "Y": 0.1951
            },
            "LeftMargin": 18.0,
            "RightMargin": 14.0,
            "TopMargin": 54.0,
            "BottomMargin": 12.0,
            "Tag": 674,
            "ActionTag": -1540087722,
            "Size": {
              "X": 50.0,
              "Y": 16.0
            },
            "Name": "lbl_num",
            "ctype": "TextObjectData"
          }
        ],
        "Size": {
          "X": 82.0,
          "Y": 82.0
        },
        "Name": "root",
        "ctype": "LayerObjectData"
      },
      "ctype": "GameProjectData"
    }
  },
  "Type": "Layer"
}